[
  {
    "id": "princeton-A5101842581",
    "name": "Chan‐Jin Park",
    "title": "Professor at Princeton University",
    "department": "Dentistry",
    "school": "Princeton",
    "location": "Princeton, NJ",
    "specific_location": "Princeton, NJ",
    "research_areas": "Dental Implant Techniques and Outcomes; Dental materials and restorations; Bone Tissue Engineering Materials; Orthopaedic implants and arthroplasty; Temporomandibular Joint Disorders",
    "website": "",
    "email": "",
    "h_index": "21",
    "lab_techniques": "Oral Surgery, Orthodontics, Biomedical Engineering, Surgery, Complementary and Manual Therapy, Medicine, Materials science, Dentistry, Dental Implant Techniques and Outcomes, Dental materials and restorations",
    "google_scholar": ""
  }
]