[
  {
    "schema_version": "2.0",
    "id": "dhruv-grewal-boston-university",
    "name": "Dhruv Grewal",
    "name_alternatives": [],
    "affiliation": {
      "school": "Boston University",
      "affiliation": "Boston University",
      "department": "Business, Management and Accounting",
      "department_category": "default",
      "title": "",
      "location": "Boston, MA",
      "specific_location": "Boston, MA"
    },
    "contact": {
      "email": "bagile@babson.edu",
      "email_confidence": "MEDIUM",
      "website": "https://business.rice.edu/person/dhruv-grewal",
      "website_confidence": "HIGH",
      "phone": "",
      "google_scholar_id": "",
      "google_scholar_url": ""
    },
    "metrics": {
      "h_index": "",
      "h_index_source": "",
      "h_index_updated": "",
      "citations_total": null,
      "i10_index": null,
      "works_count": null
    },
    "research": {
      "areas": "",
      "topics": [],
      "techniques": []
    },
    "publications": {
      "recent_papers": []
    },
    "funding": {
      "nsf_awards": [],
      "nsf_grants_count": 0,
      "co_investigators": []
    },
    "data_quality": {
      "status": "complete",
      "website_confidence": "high",
      "email_confidence": "medium",
      "confidence": "HIGH",
      "confidence_reason": "",
      "last_updated": "2026-03-19",
      "sources": [
        "master_faculty_database.csv"
      ]
    }
  },
  {
    "schema_version": "2.0",
    "id": "jeffrey-franks-boston-university",
    "name": "Jeffrey Franks",
    "name_alternatives": [],
    "affiliation": {
      "school": "Boston University",
      "affiliation": "Boston University",
      "department": "Business, Management and Accounting",
      "department_category": "default",
      "title": "",
      "location": "Boston, MA",
      "specific_location": "Boston, MA"
    },
    "contact": {
      "email": "jeff.franks@vanderbilt.edu",
      "email_confidence": "MEDIUM",
      "website": "https://www.vanderbilt.edu/psychological_sciences/bio/jeffery-franks",
      "website_confidence": "MEDIUM",
      "phone": "",
      "google_scholar_id": "",
      "google_scholar_url": ""
    },
    "metrics": {
      "h_index": "",
      "h_index_source": "",
      "h_index_updated": "",
      "citations_total": null,
      "i10_index": null,
      "works_count": null
    },
    "research": {
      "areas": "",
      "topics": [],
      "techniques": []
    },
    "publications": {
      "recent_papers": []
    },
    "funding": {
      "nsf_awards": [],
      "nsf_grants_count": 0,
      "co_investigators": []
    },
    "data_quality": {
      "status": "complete",
      "website_confidence": "medium",
      "email_confidence": "medium",
      "confidence": "MEDIUM",
      "confidence_reason": "",
      "last_updated": "2026-03-19",
      "sources": [
        "master_faculty_database.csv"
      ]
    }
  },
  {
    "schema_version": "2.0",
    "id": "jennifer-rowley-boston-university",
    "name": "Jennifer Rowley",
    "name_alternatives": [],
    "affiliation": {
      "school": "Boston University",
      "affiliation": "Boston University",
      "department": "Business, Management and Accounting",
      "department_category": "default",
      "title": "",
      "location": "Boston, MA",
      "specific_location": "Boston, MA"
    },
    "contact": {
      "email": "jrow@bu.edu",
      "email_confidence": "HIGH",
      "website": "https://www.bu.edu/wll/profile/jennifer-row/",
      "website_confidence": "HIGH",
      "phone": "",
      "google_scholar_id": "",
      "google_scholar_url": ""
    },
    "metrics": {
      "h_index": "",
      "h_index_source": "",
      "h_index_updated": "",
      "citations_total": null,
      "i10_index": null,
      "works_count": null
    },
    "research": {
      "areas": "",
      "topics": [],
      "techniques": []
    },
    "publications": {
      "recent_papers": []
    },
    "funding": {
      "nsf_awards": [],
      "nsf_grants_count": 0,
      "co_investigators": []
    },
    "data_quality": {
      "status": "complete",
      "website_confidence": "high",
      "email_confidence": "high",
      "confidence": "HIGH",
      "confidence_reason": "",
      "last_updated": "2026-03-19",
      "sources": [
        "master_faculty_database.csv"
      ]
    }
  },
  {
    "schema_version": "2.0",
    "id": "laurence-j-kotlikoff-boston-university",
    "name": "Laurence J. Kotlikoff",
    "name_alternatives": [],
    "affiliation": {
      "school": "Boston University",
      "affiliation": "Boston University",
      "department": "Business, Management and Accounting",
      "department_category": "default",
      "title": "",
      "location": "Boston, MA",
      "specific_location": "Boston, MA"
    },
    "contact": {
      "email": "kotlikoff@bu.edu",
      "email_confidence": "HIGH",
      "website": "https://www.bu.edu/econ/profile/laurence-j-kotlikoff/",
      "website_confidence": "HIGH",
      "phone": "",
      "google_scholar_id": "",
      "google_scholar_url": ""
    },
    "metrics": {
      "h_index": "",
      "h_index_source": "",
      "h_index_updated": "",
      "citations_total": null,
      "i10_index": null,
      "works_count": null
    },
    "research": {
      "areas": "",
      "topics": [],
      "techniques": []
    },
    "publications": {
      "recent_papers": []
    },
    "funding": {
      "nsf_awards": [],
      "nsf_grants_count": 0,
      "co_investigators": []
    },
    "data_quality": {
      "status": "complete",
      "website_confidence": "high",
      "email_confidence": "high",
      "confidence": "HIGH",
      "confidence_reason": "",
      "last_updated": "2026-03-19",
      "sources": [
        "master_faculty_database.csv"
      ]
    }
  }
]
