[
  {
    "id": "nsf-2538354",
    "name": "Kusali Gamage",
    "title": "Principal Investigator",
    "department": "Geosciences",
    "school": "Austin Community College",
    "location": "AUSTIN, TX",
    "research_areas": [
      "Geosciences",
      "Innovation for Critical Minerals: U.S. Sri Lanka Workshop on Graphite Research and Development"
    ],
    "website": "",
    "email": [
      "kgamage@austincc.edu"
    ],
    "h_index": "",
    "lab_techniques": [],
    "specific_location": "AUSTIN, TX",
    "nsf_awards": [
      {
        "award_number": "2538354",
        "title": "Innovation for Critical Minerals: U.S. Sri Lanka Workshop on Graphite Research and Development",
        "amount": "$49,999.00",
        "program": "XC-Crosscutting Activities Pro",
        "end_date": "08/31/2026",
        "directorate": "GEO"
      }
    ],
    "nsf_grants_count": 1,
    "co_investigators": [
      "Harold H Stowell hstowell@ua.edu",
      "Rudrajit Mitra rudrajit.mitra@sdsmt.edu",
      "Jonathan Toma jonathan.toma@yale.edu"
    ]
  }
]