[
  {
    "id": "nsf-2409955",
    "name": "Aidan W Short",
    "title": "Principal Investigator",
    "department": "Biological Sciences",
    "school": "Short, Aidan William",
    "location": "Eugene, OR",
    "research_areas": [
      "Biological Sciences",
      "Postdoctoral Fellowship: PRFB: Estimating the role of floral isolation in complex trait evolution an..."
    ],
    "website": "",
    "email": [],
    "h_index": "",
    "lab_techniques": [],
    "specific_location": "Eugene, OR",
    "nsf_awards": [
      {
        "award_number": "2409955",
        "title": "Postdoctoral Fellowship: PRFB: Estimating the role of floral isolation in complex trait evolution and plant speciation",
        "amount": "$249,000.00",
        "program": "NPGI PostDoc Rsrch Fellowship",
        "end_date": "12/31/2027",
        "directorate": "BIO"
      }
    ],
    "nsf_grants_count": 1
  }
]