[
  {
    "id": "nsf-2401770",
    "name": "Caroline D Huang",
    "title": "Principal Investigator",
    "department": "Mathematical and Physical Sciences",
    "school": "Huang, Caroline",
    "location": "Cambridge, MA",
    "research_areas": [
      "Mathematical and Physical Sciences",
      "Postdoctoral Fellowship: AAPF: Cosmology with Most Massive Asymptotic Giant Branch Stars"
    ],
    "website": "",
    "email": [],
    "h_index": "",
    "lab_techniques": [],
    "specific_location": "Cambridge, MA",
    "nsf_awards": [
      {
        "award_number": "2401770",
        "title": "Postdoctoral Fellowship: AAPF: Cosmology with Most Massive Asymptotic Giant Branch Stars",
        "amount": "$330,000.00",
        "program": "NSF ASTRON & ASTROPHY PSTDC FE",
        "end_date": "09/30/2027",
        "directorate": "MPS"
      }
    ],
    "nsf_grants_count": 1
  }
]